jsonkeys/__init__.py
jsonkeys/jsonkeys.py
jsonkeys-0.0.1.dist-info/METADATA
jsonkeys-0.0.1.dist-info/WHEEL
jsonkeys-0.0.1.dist-info/entry_points.txt
jsonkeys-0.0.1.dist-info/licenses/LICENSE
jsonkeys-0.0.1.dist-info/RECORD
